{
  "name": "Vijal Chauhan (2023-27)",
  "location": "Panipat, Haryana, India",
  "branch": "ChE",
  "bio": "Pre-Final Year Student at Rajiv Gandhi Institute of Petroleum Technology",
  "avatar": "https://res.cloudinary.com/djiq6jrn3/image/upload/v1752601508/Vijal23_bibwy8.jpg",
  "portfolio": "#",
  "skills": [
    "Canva",
    "Microsoft PowerPoint",
    "Hindi Editorial",
    "Primary Teaching",
    "Engineering",
    "Chemical Engineering",
    "Python",
    "UX Design",
    "Figma",
    "Design Thinking",
    "User Interface Design",
    "Wireframing and Prototyping",
    "AutoCAD",
    "Writing",
    "Peer Reviewer",
    "Google Analytics"
  ],
  "social": {
    "LinkedIn": "http://www.linkedin.com/in/vijal-chauhan-62742a288"
  }
}
